{
	"preload": {
		"ATLAS_JSON_ARRAYS": [
			{ "key": "assets0001", "url": "src/assets/images/assets0001" }
		],
		"IMAGES": [
			{ "key": "bg", "url": "src/assets/images/bg/e01bg0005.jpg" }
		],
		"AUDIO": [
			{ "key": "music", "url": "src/assets/audio/music/music1.mp3" }
		],
		"JSON": [
			{ "key": "board_frame1", "url": "src/assets/data/board_frame1.json" },

			{ "key": "ball_big1", "url": "src/assets/data/assets0001/ball_big1.json" },
			{ "key": "pusher1", "url": "src/assets/data/assets0001/pusher1.json" },
			{ "key": "pusher1_lt", "url": "src/assets/data/assets0001/pusher1_lt.json" },
			{ "key": "pusher1_rt", "url": "src/assets/data/assets0001/pusher1_rt.json" },
			{ "key": "pusher1_lb", "url": "src/assets/data/assets0001/pusher1_lb.json" },
			{ "key": "pusher1_rb", "url": "src/assets/data/assets0001/pusher1_rb.json" },

			{ "key": "drone1", "url": "src/assets/data/assets0001/drone1.json" },
			{ "key": "debris_drone1", "url": "src/assets/data/assets0001/debris_drone1.json" },
			{ "key": "debris_drone2", "url": "src/assets/data/assets0001/debris_drone2.json" },
			{ "key": "debris_drone3", "url": "src/assets/data/assets0001/debris_drone3.json" },
			{ "key": "debris_drone4", "url": "src/assets/data/assets0001/debris_drone4.json" },

			{ "key": "drone1_engine", "url": "src/assets/data/assets0001/drone1_engine.json" },
			{ "key": "debris_drone1_engine1_1", "url": "src/assets/data/assets0001/debris_drone1_engine1_1.json" },
			{ "key": "debris_drone1_engine1_2", "url": "src/assets/data/assets0001/debris_drone1_engine1_2.json" },
			{ "key": "debris_drone1_engine1_3", "url": "src/assets/data/assets0001/debris_drone1_engine1_3.json" },

			{ "key": "fire", "url": "src/assets/data/assets0001/fire.json" },

			{ "key": "sensor_ground", "url": "src/assets/data/assets0001/sensor_ground.json" },

			{ "key": "sensor_success1", "url": "src/assets/data/assets0001/sensor_success1.json" },
			{ "key": "sensor_teleport1", "url": "src/assets/data/assets0001/sensor_teleport1.json" },

			{ "key": "jewel1", "url": "src/assets/data/jewel1.json" },

			{ "key": "brick1_3", "url": "src/assets/data/assets0001/brick1_3.json" },
			{ "key": "brick1_3_sdd", "url": "src/assets/data/assets0001/brick1_3_sdd.json" },
			{ "key": "brick1_3_1", "url": "src/assets/data/assets0001/brick1_3_1.json" },
			{ "key": "brick1_3_1_1", "url": "src/assets/data/assets0001/brick1_3_1_1.json" },
			{ "key": "brick1_3_1_2", "url": "src/assets/data/assets0001/brick1_3_1_2.json" },
			{ "key": "brick1_3_2", "url": "src/assets/data/assets0001/brick1_3_2.json" },
			{ "key": "brick1_3_2_1", "url": "src/assets/data/assets0001/brick1_3_2_1.json" },
			{ "key": "brick1_3_2_2", "url": "src/assets/data/assets0001/brick1_3_2_2.json" },

			{ "key": "debris_atom1", "url": "src/assets/data/assets0001/debris_atom1.json" },

			{ "key": "pharao_dynamic", "url": "src/assets/data/assets0001/pharao_dynamic.json" },
			{ "key": "debris_pharao2", "url": "src/assets/data/assets0001/debris_pharao2.json" },
			{ "key": "debris_pharao3", "url": "src/assets/data/assets0001/debris_pharao3.json" },

			{ "key": "beam1", "url": "src/assets/data/assets0001/beam1.json" },
			{ "key": "debris_beam1", "url": "src/assets/data/assets0001/debris_beam1.json" },
			{ "key": "debris_beam2", "url": "src/assets/data/assets0001/debris_beam2.json" },
			{ "key": "debris_beam3", "url": "src/assets/data/assets0001/debris_beam3.json" }
		],
		"PHYSICS": [
			{ "key": "physicsData", "url": "src/assets/data/assets0001/physicsData.json" }
		]
	}, 
	"bg": "bg",
	"balls": 20,
	"tasks": 1,
	"fails": 4,
	"objects": [
		{
			"name": "bf1",
			"template": "board_frame1",
			"x": 0,
			"y": 0,
			"layer": 0
		},

		{
			"name": "brick11",
			"template": "brick1_3",
			"x": 800,
			"y": 919,
			"layer": 2
		},
		{
			"name": "brick12",
			"template": "brick1_3",
			"x": 800,
			"y": 808,
			"layer": 2,
			"isDisabled": false
		},
		{
			"name": "brick13",
			"template": "brick1_3",
			"x": 800,
			"y": 696,
			"layer": 2
		},

		{
			"name": "sensorGround",
			"template": "sensor_ground"
		},

		{
			"name": "Pusher",
			"template": "pusher1",
			"x": 1720,
			"y": 800
		},
		{
			"name": "pusher1_lb",
			"template": "pusher1_lb",
			"x": 1626,
			"y": 890
		},
		{
			"name": "pusher1_rb",
			"template": "pusher1_rb",
			"x": 1809,
			"y": 890
		},
		{
			"name": "pusher1_lt",
			"template": "pusher1_lt",
			"x": 1642,
			"y": 655
		},
		{
			"name": "pusher1_rt",
			"template": "pusher1_rt",
			"x": 1797,
			"y": 655
		},


		{
			"name": "pharao3",
			"template": "pharao_dynamic",
			"x": 780,
			"y": 550,
			"layer": 2
		},

		{
			"name": "brick1sdd1",
			"template": "brick1_3_sdd",
			"x": 1000,
			"y": 50,
			"layer": 2
		},
		{
			"name": "brick1sdd2",
			"template": "brick1_3_sdd",
			"x": 830,
			"y": 65,
			"layer": 2
		},
		{
			"name": "brick1sdd3",
			"template": "brick1_3_sdd",
			"x": 660,
			"y": 80,
			"layer": 2
		},

		{
			"name": "Beam1",
			"template": "beam1",
			"lives": 19,
			"layer": 3
		},

		{
			"name": "drone1",
			"template": "drone1",
			"x": 1500,
			"y": 300,
			"layer": 2
		},

		{
			"name": "Ball1",
			"template": "ball_big1",
			"x": 1720,
			"y": 710,
			"layer": 2
		}

	]
}
